nanolink/__init__.py
nanolink/command.py
nanolink/connection.py
nanolink/grpc_service.py
nanolink/mcp_server.py
nanolink/metrics.py
nanolink/sanitize.py
nanolink/server.py
nanolink/proto/__init__.py
nanolink/proto/nanolink_pb2.py
nanolink/proto/nanolink_pb2_grpc.py
tests/__init__.py
tests/test_command.py
tests/test_metrics.py
tests/test_server.py
kkape_nanolink-0.4.2.dist-info/METADATA
kkape_nanolink-0.4.2.dist-info/WHEEL
kkape_nanolink-0.4.2.dist-info/top_level.txt
kkape_nanolink-0.4.2.dist-info/RECORD
