Metadata-Version: 2.4
Name: kkape-nanolink
Version: 0.4.2
Summary: Python SDK for NanoLink monitoring system
Author-email: chenqi92 <hi@kkape.com>
License: Apache-2.0
Project-URL: Homepage, https://github.com/chenqi92/NanoLink
Project-URL: Documentation, https://github.com/chenqi92/NanoLink#readme
Project-URL: Repository, https://github.com/chenqi92/NanoLink
Project-URL: Issues, https://github.com/chenqi92/NanoLink/issues
Keywords: monitoring,metrics,agent,grpc,kkape
Classifier: Development Status :: 4 - Beta
Classifier: Intended Audience :: Developers
Classifier: License :: OSI Approved :: Apache Software License
Classifier: Operating System :: OS Independent
Classifier: Programming Language :: Python :: 3
Classifier: Programming Language :: Python :: 3.9
Classifier: Programming Language :: Python :: 3.10
Classifier: Programming Language :: Python :: 3.11
Classifier: Programming Language :: Python :: 3.12
Classifier: Programming Language :: Python :: 3.13
Classifier: Topic :: System :: Monitoring
Classifier: Topic :: Software Development :: Libraries :: Python Modules
Requires-Python: >=3.9
Requires-Dist: protobuf>=5.29.0
Requires-Dist: grpcio>=1.68.0
Requires-Dist: grpcio-tools>=1.68.0
Provides-Extra: dev
Requires-Dist: pytest>=7.4.0; extra == "dev"
Requires-Dist: pytest-asyncio>=0.21.0; extra == "dev"
Requires-Dist: pytest-cov>=4.1.0; extra == "dev"
Requires-Dist: black>=23.0.0; extra == "dev"
Requires-Dist: ruff>=0.2.4; extra == "dev"
Requires-Dist: mypy>=1.7.0; extra == "dev"
